adapt/__init__.py
adapt/path.py
adapt/refine.py
adapt/snap.py
bbnadapt-2019.1.dist-info/LICENSE
bbnadapt-2019.1.dist-info/METADATA
bbnadapt-2019.1.dist-info/WHEEL
bbnadapt-2019.1.dist-info/top_level.txt
bbnadapt-2019.1.dist-info/RECORD
